deerlab/__init__.py
deerlab/bg_models.py
deerlab/bootstrap_analysis.py
deerlab/classes.py
deerlab/constants.py
deerlab/correctphase.py
deerlab/correctzerotime.py
deerlab/dd_models.py
deerlab/deerload.py
deerlab/dipolarbackground.py
deerlab/dipolarkernel.py
deerlab/dipolarmodel.py
deerlab/distancerange.py
deerlab/diststats.py
deerlab/fftspec.py
deerlab/fit.py
deerlab/fitresult.py
deerlab/model.py
deerlab/noiselevel.py
deerlab/profile_analysis.py
deerlab/regoperator.py
deerlab/selregparam.py
deerlab/solvers.py
deerlab/utils.py
deerlab/whitegaussnoise.py
deerlab-1.1.5.dist-info/licenses/LICENSE
deerlab-1.1.5.dist-info/METADATA
deerlab-1.1.5.dist-info/WHEEL
deerlab-1.1.5.dist-info/top_level.txt
deerlab-1.1.5.dist-info/RECORD
