Metadata-Version: 2.4
Name: DeerLab
Version: 1.1.5
Summary: Comprehensive package for data analysis of dipolar EPR spectroscopy
Home-page: https://github.com/JeschkeLab/DeerLab
Author: Luis Fábregas Ibáñez , Stefan Stoll and other contributors
License: LICENSE.txt
Project-URL: Documentation, https://jeschkelab.github.io/DeerLab/
Project-URL: Source, https://github.com/JeschkeLab/DeerLab
Keywords: data,analysis,modeling,least-squares,EPR,spectroscopy,DEER,PELDOR
Classifier: Development Status :: 5 - Production/Stable
Classifier: Intended Audience :: Science/Research
Classifier: License :: OSI Approved :: MIT License
Classifier: Operating System :: Microsoft :: Windows
Classifier: Operating System :: MacOS
Classifier: Operating System :: POSIX :: Linux
Classifier: Programming Language :: Python :: 3.9
Classifier: Programming Language :: Python :: 3.10
Classifier: Programming Language :: Python :: 3.11
Classifier: Programming Language :: Python :: 3.12
Classifier: Topic :: Scientific/Engineering :: Chemistry
Requires-Python: >=3.9
License-File: LICENSE
Requires-Dist: numpy>=2.0
Requires-Dist: cvxopt>=1.0.0
Requires-Dist: scipy>=1.11
Requires-Dist: joblib>=1.0.0
Requires-Dist: dill>=0.3.0
Requires-Dist: tqdm>=4.51.0
Requires-Dist: matplotlib>=3.6.0
Requires-Dist: memoization>=0.3.1
Requires-Dist: pytest>=6.2.2
Requires-Dist: setuptools>=53.0.0
Requires-Dist: numexpr>=2.7.3
Requires-Dist: quadprog>=0.1.11; python_version <= "3.10"
Dynamic: author
Dynamic: classifier
Dynamic: description
Dynamic: description-content-type
Dynamic: home-page
Dynamic: keywords
Dynamic: license
Dynamic: license-file
Dynamic: project-url
Dynamic: requires-dist
Dynamic: requires-python
Dynamic: summary
